jpg_sorter/__init__.py
jpg_sorter/sorter.py
jpg_sorter/icons/wired/icons8-add-file.png
jpg_sorter/icons/wired/icons8-add-folder.png
jpg_sorter/icons/wired/icons8-checked.png
jpg_sorter/icons/wired/icons8-close-window.png
jpg_sorter/icons/wired/icons8-delete-file.png
jpg_sorter/icons/wired/icons8-down.png
jpg_sorter/icons/wired/icons8-gps.png
jpg_sorter/icons/wired/icons8-loader.png
jpg_sorter/icons/wired/icons8-location.png
jpg_sorter/icons/wired/icons8-rotate-left.png
jpg_sorter/icons/wired/icons8-rotate-right.png
jpg_sorter/icons/wired/icons8-save.png
jpg_sorter/icons/wired/icons8-time-machine.png
jpg_sorter/icons/wired/icons8-up.png
jpg_sorter/icons/wired/icons8-zoom-in.png
jpg_sorter/icons/wired/icons8-zoom-out.png
jpg_sorter-1.1.1.dist-info/LICENSE
jpg_sorter-1.1.1.dist-info/METADATA
jpg_sorter-1.1.1.dist-info/WHEEL
jpg_sorter-1.1.1.dist-info/entry_points.txt
jpg_sorter-1.1.1.dist-info/top_level.txt
jpg_sorter-1.1.1.dist-info/RECORD
