Metadata-Version: 2.1
Name: jpg-sorter
Version: 1.1.1
Summary: Python GUI tool that allows EXIF data change.
Home-page: https://gitlab.com/zbij/jpgSorter
Author: Zbigniew Kurzynski
Author-email: zbij@wp.pl
License: MIT
Platform: UNKNOWN
Classifier: Programming Language :: Python :: 3
Classifier: License :: OSI Approved :: MIT License
Classifier: Operating System :: OS Independent
Requires-Python: >=3.7
Requires-Dist: PyQt5 (>=5.14.0)
Requires-Dist: piexif (>=1.0.13)
